MANIFEST.in
README.rst
setup.py
kongfu_plugs.egg-info/PKG-INFO
kongfu_plugs.egg-info/SOURCES.txt
kongfu_plugs.egg-info/dependency_links.txt
kongfu_plugs.egg-info/not-zip-safe
kongfu_plugs.egg-info/top_level.txt
plugs/__init__.py
plugs/top/__init__.py
plugs/top/api/__init__.py
plugs/top/api/base.py
plugs/top/api/rest/AlibabaAliqinFcFlowChargeRequest.py
plugs/top/api/rest/AlibabaAliqinFcFlowGradeRequest.py
plugs/top/api/rest/AlibabaAliqinFcFlowQueryRequest.py
plugs/top/api/rest/AlibabaAliqinFcSmsNumQueryRequest.py
plugs/top/api/rest/AlibabaAliqinFcSmsNumSendRequest.py
plugs/top/api/rest/AlibabaAliqinFcTtsNumSinglecallRequest.py
plugs/top/api/rest/AlibabaAliqinFcVoiceNumDoublecallRequest.py
plugs/top/api/rest/AlibabaAliqinFcVoiceNumSinglecallRequest.py
plugs/top/api/rest/AlibabaGeoipGetRequest.py
plugs/top/api/rest/AppipGetRequest.py
plugs/top/api/rest/AreasGetRequest.py
plugs/top/api/rest/HttpdnsGetRequest.py
plugs/top/api/rest/KfcKeywordSearchRequest.py
plugs/top/api/rest/TimeGetRequest.py
plugs/top/api/rest/TopAuthTokenCreateRequest.py
plugs/top/api/rest/TopAuthTokenRefreshRequest.py
plugs/top/api/rest/TopIpoutGetRequest.py
plugs/top/api/rest/TopatsResultGetRequest.py
plugs/top/api/rest/TopatsTaskDeleteRequest.py
plugs/top/api/rest/__init__.py