Metadata-Version: 1.1
Name: kongfu-plugs
Version: 0.0.1a
Summary: Plugs is a collection project for kongfu project
Home-page: https://git.oschina.net/uniyes/kongfu-plugs
Author: Uniyes.com
Author-email: company@Uniyes.com
License: MIT
Keywords: please don't use this library for anything
Platform: UNKNOWN
Classifier: Intended Audience :: Developers
Classifier: License :: OSI Approved :: MIT License
Classifier: Programming Language :: Python
Classifier: Programming Language :: Python :: 2.7
